nym/__init__.py
nym/cli.py
nym/fast.cpython-310-x86_64-linux-gnu.so
nym/slow.py
nym/fast/__init__.py
nym/fast/fast.nim
nym/fast/fast.nimble
nym-0.1.2.dist-info/LICENSE
nym-0.1.2.dist-info/METADATA
nym-0.1.2.dist-info/WHEEL
nym-0.1.2.dist-info/entry_points.txt
nym-0.1.2.dist-info/top_level.txt
nym-0.1.2.dist-info/RECORD
