Metadata-Version: 2.1
Name: nym
Version: 0.1.2
Summary: Nim extension for Python, example project
Home-page: https://github.com/gmagno/nym
Author: Goncalo Magno
Author-email: goncalo.magno@gmail.com
License: MIT license
Keywords: nym
Platform: UNKNOWN
Classifier: Development Status :: 2 - Pre-Alpha
Classifier: Intended Audience :: Developers
Classifier: License :: OSI Approved :: MIT License
Classifier: Natural Language :: English
Classifier: Programming Language :: Python :: 3
Classifier: Programming Language :: Python :: 3.10
Requires-Python: >=3.10
License-File: LICENSE
Requires-Dist: Click (>=7.0)
Requires-Dist: nimporter
